MANIFEST.in
README.rst
setup.py
docs/HISTORY.txt
docs/LICENSE.GPL
docs/LICENSE.txt
docs/label_jar.png
docs/label_support.png
ftw/__init__.py
ftw.labels.egg-info/PKG-INFO
ftw.labels.egg-info/SOURCES.txt
ftw.labels.egg-info/dependency_links.txt
ftw.labels.egg-info/entry_points.txt
ftw.labels.egg-info/namespace_packages.txt
ftw.labels.egg-info/not-zip-safe
ftw.labels.egg-info/requires.txt
ftw.labels.egg-info/top_level.txt
ftw/labels/__init__.py
ftw/labels/adapters.zcml
ftw/labels/config.py
ftw/labels/configure.zcml
ftw/labels/indexer.py
ftw/labels/interfaces.py
ftw/labels/jar.py
ftw/labels/labeling.py
ftw/labels/lawgiver.zcml
ftw/labels/permissions.zcml
ftw/labels/profiles.zcml
ftw/labels/setuphandler.py
ftw/labels/testing.py
ftw/labels/utils.py
ftw/labels/Extensions/install.py
ftw/labels/browser/__init__.py
ftw/labels/browser/configure.zcml
ftw/labels/browser/labeling.py
ftw/labels/browser/labelsjar.py
ftw/labels/browser/resources/edit_labels.png
ftw/labels/browser/resources/ftw-labels.css
ftw/labels/browser/resources/ftw-labels.js
ftw/labels/browser/resources/select2-spinner.gif
ftw/labels/browser/resources/select2.css
ftw/labels/browser/resources/select2.min.js
ftw/labels/browser/resources/select2.png
ftw/labels/browser/resources/select2x2.png
ftw/labels/browser/resources/settings.png
ftw/labels/browser/templates/edit_label.pt
ftw/labels/locales/ftw.labels.pot
ftw/labels/locales/de/LC_MESSAGES/ftw.labels.po
ftw/labels/locales/fr/LC_MESSAGES/ftw.labels.po
ftw/labels/portlets/__init__.py
ftw/labels/portlets/assignments.py
ftw/labels/portlets/configure.zcml
ftw/labels/portlets/interfaces.py
ftw/labels/portlets/labeljar.pt
ftw/labels/portlets/labeljar.py
ftw/labels/profiles/default/cssregistry.xml
ftw/labels/profiles/default/ftw.labels.setuphandlers.txt
ftw/labels/profiles/default/jsregistry.xml
ftw/labels/profiles/default/metadata.xml
ftw/labels/profiles/default/portlets.xml
ftw/labels/profiles/default/rolemap.xml
ftw/labels/profiles/uninstall/.gitkeep
ftw/labels/profiles/uninstall/cssregistry.xml
ftw/labels/profiles/uninstall/ftw.labels.setuphandlers.txt
ftw/labels/profiles/uninstall/jsregistry.xml
ftw/labels/profiles/uninstall/portlets.xml
ftw/labels/profiles/uninstall/rolemap.xml
ftw/labels/tests/__init__.py
ftw/labels/tests/builders.py
