Metadata-Version: 1.1
Name: ftw.labels
Version: 1.3.1
Summary: A Plone addon for labels.
Home-page: https://github.com/4teamwork/ftw.labels
Author: 4teamwork AG
Author-email: mailto:info@4teamwork.ch
License: GPL2
Keywords: ftw labels
Platform: UNKNOWN
Classifier: Framework :: Plone
Classifier: Framework :: Plone :: 4.3
Classifier: Intended Audience :: Developers
Classifier: Topic :: Software Development :: Libraries :: Python Modules
